{
  "RSpec": {
    "coverage": {
      "/Users/ruezheng/turing/1module/projects/night_writer/lib/braille_translator.rb": {
        "lines": [
          1,
          null,
          1,
          null,
          1,
          80,
          null,
          null,
          1,
          80,
          null,
          null,
          1,
          5,
          5,
          75,
          null,
          5,
          null,
          null,
          1,
          4,
          4,
          4,
          4,
          48,
          48,
          48,
          null,
          4,
          null,
          null,
          1,
          2,
          2,
          2,
          2,
          null,
          null
        ]
      },
      "/Users/ruezheng/turing/1module/projects/night_writer/lib/dictionary.rb": {
        "lines": [
          1,
          1,
          null,
          null,
          1,
          null,
          80,
          null,
          null,
          null,
          null,
          null,
          null,
          null,
          null,
          null,
          null,
          null,
          null,
          null,
          null,
          null,
          null,
          null,
          null,
          null,
          null,
          null,
          null,
          null,
          null,
          null,
          null,
          null,
          80,
          null,
          null
        ]
      }
    },
    "timestamp": 1650825819
  }
}
